turnsole/__init__.py
turnsole/convenience.py
turnsole/encodings.py
turnsole/model.py
turnsole/paths.py
turnsole/pdf_tools.py
turnsole/face_utils/__init__.py
turnsole/face_utils/agedetector.py
turnsole/face_utils/facedetector.py
turnsole/nets/__init__.py
turnsole/nets/efficientnet.py
turnsole/ocr_engine/__init__.py
turnsole/ocr_engine/ADC/__init__.py
turnsole/ocr_engine/ADC/angle_detector.py
turnsole/ocr_engine/CRNN/__init__.py
turnsole/ocr_engine/CRNN/alphabets.py
turnsole/ocr_engine/CRNN/text_rec.py
turnsole/ocr_engine/DBNet/__init__.py
turnsole/ocr_engine/DBNet/text_detector.py
turnsole/ocr_engine/object_det/__init__.py
turnsole/ocr_engine/object_det/utils.py
turnsole/ocr_engine/signature_det/__init__.py
turnsole/ocr_engine/signature_det/utils.py
turnsole/ocr_engine/utils/__init__.py
turnsole/ocr_engine/utils/read_data.py
turnsole/video/__init__.py
turnsole/video/count_frames.py
turnsole/video/filevideostream.py
turnsole/video/fps.py
turnsole/video/pivideostream.py
turnsole/video/videostream.py
turnsole/video/webcamvideostream.py
turnsole-0.0.27.dist-info/LICENSE
turnsole-0.0.27.dist-info/METADATA
turnsole-0.0.27.dist-info/WHEEL
turnsole-0.0.27.dist-info/top_level.txt
turnsole-0.0.27.dist-info/RECORD
