Metadata-Version: 2.1
Name: turnsole
Version: 0.0.27
Summary: A series of convenience functions make your machine learning project easier
Home-page: https://github.com/Antonio-hi/turnsole
Author: Kui Lyu
Author-email: 9428.al@gmail.com
Project-URL: Bug Tracker, https://github.com/Antonio-hi/turnsole/issues
Classifier: Programming Language :: Python :: 3
Classifier: License :: OSI Approved :: MIT License
Classifier: Operating System :: OS Independent
Requires-Python: >=3.6
License-File: LICENSE
